moler/__init__.py
moler/abstract_moler_connection.py
moler/asyncio_runner.py
moler/command.py
moler/command_scheduler.py
moler/connection.py
moler/connection_factory.py
moler/connection_observer.py
moler/event.py
moler/event_awaiter.py
moler/exceptions.py
moler/helpers.py
moler/instance_loader.py
moler/moler_connection_for_single_thread_runner.py
moler/observable_connection.py
moler/observer_thread_wrapper.py
moler/publisher.py
moler/runner.py
moler/runner_factory.py
moler/runner_single_thread.py
moler/scheduler.py
moler/threaded_moler_connection.py
moler/cmd/__init__.py
moler/cmd/commandchangingprompt.py
moler/cmd/commandtextualgeneric.py
moler/cmd/adb/__init__.py
moler/cmd/adb/adb_shell.py
moler/cmd/adb/generic_adb_command.py
moler/cmd/at/__init__.py
moler/cmd/at/at.py
moler/cmd/at/attach.py
moler/cmd/at/create_pdu_session.py
moler/cmd/at/cu.py
moler/cmd/at/detach.py
moler/cmd/at/enable_echo.py
moler/cmd/at/exit_serial_proxy.py
moler/cmd/at/genericat.py
moler/cmd/at/get_apns.py
moler/cmd/at/get_attach_state.py
moler/cmd/at/get_cell_id.py
moler/cmd/at/get_cell_id_gprs.py
moler/cmd/at/get_cell_id_lte.py
moler/cmd/at/get_cell_id_nr.py
moler/cmd/at/get_functionality_level.py
moler/cmd/at/get_imei.py
moler/cmd/at/get_imsi.py
moler/cmd/at/get_ip.py
moler/cmd/at/get_manufacturer_id.py
moler/cmd/at/get_product_info.py
moler/cmd/at/get_revision_id.py
moler/cmd/at/gt_cell_lock.py
moler/cmd/at/plink_serial.py
moler/cmd/at/quectel_lock_nr_earfcn.py
moler/cmd/at/quectel_network_preferences.py
moler/cmd/at/release_pdu_session.py
moler/cmd/at/run_script.py
moler/cmd/at/set_apn.py
moler/cmd/at/set_cell_id.py
moler/cmd/at/set_cell_id_gprs.py
moler/cmd/at/set_cell_id_lte.py
moler/cmd/at/set_cell_id_nr.py
moler/cmd/at/set_functionality_level.py
moler/cmd/at/set_mode.py
moler/cmd/juniper/__init__.py
moler/cmd/juniper/genericjuniper.py
moler/cmd/juniper/cli/__init__.py
moler/cmd/juniper/cli/configure.py
moler/cmd/juniper/configure/__init__.py
moler-4.5.0.dist-info/licenses/LICENSE
moler-4.5.0.dist-info/METADATA
moler-4.5.0.dist-info/WHEEL
moler-4.5.0.dist-info/top_level.txt
moler-4.5.0.dist-info/RECORD
