Metadata-Version: 2.4
Name: moler
Version: 4.5.0
Summary: Moler is a library for working with terminals, mainly for automated tests
Home-page: https://github.com/nokia/moler
Author: Nokia
License: BSD 3-Clause
Project-URL: Bug Reports, https://github.com/nokia/moler/issues
Project-URL: Source, https://github.com/nokia/moler
Keywords: testing development
Classifier: Development Status :: 5 - Production/Stable
Classifier: Environment :: Console
Classifier: Intended Audience :: Developers
Classifier: Intended Audience :: System Administrators
Classifier: Intended Audience :: Telecommunications Industry
Classifier: Topic :: Software Development :: Build Tools
Classifier: License :: OSI Approved :: BSD License
Classifier: Operating System :: POSIX
Classifier: Operating System :: Unix
Classifier: Programming Language :: Python :: 3
Classifier: Programming Language :: Python :: 3.7
Classifier: Programming Language :: Python :: 3.8
Classifier: Programming Language :: Python :: 3.9
Classifier: Programming Language :: Python :: 3.10
Classifier: Programming Language :: Python :: 3.11
Classifier: Programming Language :: Python :: 3.12
Classifier: Programming Language :: Python :: 3.13
Classifier: Programming Language :: Python :: 3.14
Classifier: Topic :: Software Development
Classifier: Topic :: Software Development :: Testing
Classifier: Topic :: System :: Networking
Requires-Python: >=3.7
License-File: LICENSE
Requires-Dist: ptyprocess; platform_system != "Windows"
Requires-Dist: pyyaml>=5.1
Requires-Dist: six
Requires-Dist: transitions
Requires-Dist: apscheduler
Requires-Dist: psutil
Requires-Dist: python-dateutil
Requires-Dist: pyserial
Requires-Dist: cryptography
Requires-Dist: paramiko
Requires-Dist: importlib-metadata
Dynamic: author
Dynamic: classifier
Dynamic: description
Dynamic: description-content-type
Dynamic: home-page
Dynamic: keywords
Dynamic: license
Dynamic: license-file
Dynamic: project-url
Dynamic: requires-dist
Dynamic: requires-python
Dynamic: summary
